{
  "groups": [
    {
      "id": "muse",
      "name": "µ's",
      "artists": [
        "µ's",
        "A-RISE",
        "Printemps",
        "BiBi",
        "lily white",
        "코우사카 호노카 (CV. 닛타 에미)",
        "아야세 에리 (CV. 난죠 요시노)",
        "미나미 코토리 (CV. 우치다 아야)",
        "소노다 우미 (CV. 미모리 스즈코)",
        "호시조라 린 (CV. 아이다 리호)",
        "니시키노 마키 (CV. Pile)",
        "토죠 노조미 (CV. 쿠스다 아이나)",
        "코이즈미 하나요 (CV. 쿠보 유리카)",
        "야자와 니코 (CV. 토쿠이 소라)"
      ],
      "color": "#E4007F"
    },
    {
      "id": "aqours",
      "name": "Aqours",
      "artists": ["Aqours"],
      "color": "#00A0E9"
    },
    {
      "id": "nijigasaki",
      "name": "虹ヶ咲学園スクールアイドル同好会",
      "artists": ["虹ヶ咲学園スクールアイドル同好会"],
      "color": "#F6B92E"
    },
    {
      "id": "liella",
      "name": "Liella!",
      "artists": ["Liella!"],
      "color": "#9B3790"
    }
  ],
  "songs": [
    [
      {
        "title": "僕らのLIVE 君とのLIFE",
        "title.ko": "우리들의 LIVE 너와의 LIFE",
        "artist": 0,
        "metadata": {
          "released": 1282662000
        }
      },
      {
        "title": "友情ノーチェンジ",
        "title.ko": "우정 노 체인지",
        "artist": 0,
        "metadata": {
          "released": 1282662000
        }
      },
      {
        "title": "Snow halation",
        "artist": 0,
        "metadata": {
          "released": 1292943600
        }
      },
      {
        "title": "baby maybe 恋のボタン",
        "title.ko": "baby maybe 사랑의 버튼",
        "artist": 0,
        "metadata": {
          "released": 1292943600
        }
      },
      {
        "title": "Love marginal",
        "artist": 2,
        "metadata": {
          "released": 1306249200
        }
      },
      {
        "title": "sweet＆sweet holiday",
        "artist": 2,
        "metadata": {
          "released": 1306249200
        }
      },
      {
        "title": "ダイヤモンドプリンセスの憂鬱",
        "title.ko": "다이아몬드 프린세스의 우울",
        "artist": 3,
        "metadata": {
          "released": 1308668400
        }
      },
      {
        "title": "ラブノベルス",
        "title.ko": "러브 노벨즈",
        "artist": 3,
        "metadata": {
          "released": 1308668400
        }
      },
      {
        "title": "知らないLove*教えてLove",
        "title.ko": "모르는 Love*가르쳐줘 Love",
        "artist": 4,
        "metadata": {
          "released": 1311692400
        }
      },
      {
        "title": "あ・の・ね・が・ん・ば・れ！",
        "title.ko": "있・잖・아・힘・을・내!",
        "artist": 4,
        "metadata": {
          "released": 1311692400
        }
      },
      {
        "title": "夏色えがおで1,2,Jump!",
        "title.ko": "여름빛 미소로 1, 2, Jump!",
        "artist": 0,
        "metadata": {
          "released": 1314111600
        }
      },
      {
        "title": "Mermaid festa vol.1",
        "artist": 0,
        "metadata": {
          "released": 1314111600
        }
      },
      {
        "title": "私たちは未来の花",
        "title.ko": "우리들은 미래의 꽃",
        "artist": 8,
        "metadata": {
          "released": 1321974000
        }
      },
      {
        "title": "スピカテリブル",
        "title.ko": "스피카 테러블",
        "artist": 7,
        "metadata": {
          "released": 1323788400
        }
      },
      {
        "title": "愛は太陽じゃない?",
        "title.ko": "사랑은 태양이 아닐까?",
        "artist": 5,
        "metadata": {
          "released": 1327417200
        }
      },
      {
        "title": "もうひとりじゃないよ",
        "title.ko": "더 이상 혼자가 아니야",
        "artist": 5,
        "metadata": {
          "released": 1327417200
        }
      },
      {
        "title": "もぎゅっと“love”で接近中！",
        "title.ko": "꼬옥 \"love\"로 접근 중!",
        "artist": 0,
        "metadata": {
          "released": 1329231600
        }
      },
      {
        "title": "愛してるばんざーい！",
        "title.ko": "사랑해 만세!",
        "artist": 0,
        "metadata": {
          "released": 1329231600
        }
      },
      {
        "title": "Mermaid festa vol.2 ~Passionate~",
        "artist": [5, 9],
        "metadata": {
          "released": 1335279600
        }
      },
      {
        "title": "Someday of my life",
        "artist": [5, 9],
        "metadata": {
          "released": 1335279600
        }
      },
      {
        "title": "恋のシグナルRin rin rin!",
        "title.ko": "사랑의 시그널 Rin rin rin!",
        "artist": [5, 9],
        "metadata": {
          "released": 1335279600
        }
      },
      {
        "title": "乙女式れんあい塾",
        "title.ko": "소녀식 연애 학원",
        "artist": [11, 13],
        "metadata": {
          "released": 1337698800
        }
      },
      {
        "title": "まほうつかいはじめました！",
        "title.ko": "마법사 시작했습니다!",
        "artist": [11, 13],
        "metadata": {
          "released": 1337698800
        }
      },
      {
        "title": "純愛レンズ",
        "title.ko": "순애 렌즈",
        "artist": [11, 13],
        "metadata": {
          "released": 1337698800
        }
      },
      {
        "title": "告白日和、です！",
        "title.ko": "고백하기 좋은 날, 입니다!",
        "artist": [7, 12],
        "metadata": {
          "released": 1340722800
        }
      },
      {
        "title": "ぶる~べりぃ♥とれいん",
        "title.ko": "블루~베리♥트레인",
        "artist": [7, 12],
        "metadata": {
          "released": 1340722800
        }
      },
      {
        "title": "孤独なHeaven",
        "title.ko": "고독한 Heaven",
        "artist": [7, 12],
        "metadata": {
          "released": 1340722800
        }
      },
      {
        "title": "soldier game",
        "artist": [6, 8, 10],
        "metadata": {
          "released": 1343142000
        }
      },
      {
        "title": "Daring!!",
        "artist": [6, 8, 10],
        "metadata": {
          "released": 1343142000
        }
      },
      {
        "title": "勇気のReason",
        "title.ko": "용기의 Reason",
        "artist": [6, 8, 10],
        "metadata": {
          "released": 1343142000
        }
      },
      {
        "title": "ありふれた悲しみの果て",
        "title.ko": "흔한 슬픔의 끝",
        "artist": [6, 8, 10],
        "metadata": {
          "released": 1343142000
        }
      },
      {
        "title": "Wonderful Rush",
        "artist": 0,
        "metadata": {
          "released": 1346770800
        }
      },
      {
        "title": "Oh,Love＆Peace!",
        "artist": 0,
        "metadata": {
          "released": 1346770800
        }
      },
      {
        "title": "Listen to my heart!!",
        "artist": [9, 12, 13],
        "metadata": {
          "released": 1350399600
        }
      },
      {
        "title": "after school NAVIGATORS",
        "artist": [9, 12, 13],
        "metadata": {
          "released": 1350399600
        }
      },
      {
        "title": "僕らは今のなかで",
        "title.ko": "우리들은 지금 속에서",
        "artist": 0,
        "metadata": {
          "released": 1358866800
        }
      },
      {
        "title": "WILD STARS",
        "artist": 0,
        "metadata": {
          "released": 1358866800
        }
      },
      {
        "title": "きっと青春が聞こえる",
        "title.ko": "분명 청춘이 들릴 거야",
        "artist": 0,
        "metadata": {
          "released": 1360076400
        }
      },
      {
        "title": "輝夜の城で踊りたい",
        "title.ko": "카구야의 성에서 춤추고 싶어",
        "artist": 0,
        "metadata": {
          "released": 1360076400
        }
      },
      {
        "title": "ススメ→トゥモロウ",
        "title.ko": "나아가→Tomorrow",
        "artist": [5, 7, 8],
        "metadata": {
          "released": 1361286000
        }
      },
      {
        "title": "START:DASH!!",
        "title.ko": "3인 버전",
        "artist": [5, 7, 8],
        "metadata": {
          "released": 1361286000
        }
      },
      {
        "title": "これからのSomeday",
        "title.ko": "앞으로 다가올 Someday",
        "artist": [5, 7, 8, 9, 10, 12, 13],
        "metadata": {
          "released": 1362495600
        }
      },
      {
        "title": "Wonder zone",
        "artist": 0,
        "metadata": {
          "released": 1362495600
        }
      },
      {
        "title": "夢なき夢は夢じゃない",
        "title.ko": "꿈이 없는 꿈은 꿈이 아니야",
        "artist": 5,
        "metadata": {
          "released": 1363878000
        }
      },
      {
        "title": "No brand girls",
        "artist": 0,
        "metadata": {
          "released": 1364914800
        }
      },
      {
        "title": "START:DASH!!",
        "artist": 0,
        "metadata": {
          "released": 1364914800
        }
      },
      {
        "title": "Private Wars",
        "artist": 1,
        "metadata": {
          "released": 1365519600
        }
      },
      {
        "title": "Anemone Heart",
        "artist": [7, 8],
        "metadata": {
          "released": 1366729200
        }
      },
      {
        "title": "なわとび",
        "title.ko": "줄넘기",
        "artist": 12,
        "metadata": {
          "released": 1369666800
        }
      },
      {
        "title": "Beat in Angel",
        "artist": [9, 10],
        "metadata": {
          "released": 1371740400
        }
      },
      {
        "title": "微熱からMystery",
        "title.ko": "미열에서 Mystery",
        "artist": 4,
        "metadata": {
          "released": 1372172400
        }
      },
      {
        "title": "キミのくせに！",
        "title.ko": "너 주제에!",
        "artist": 4,
        "metadata": {
          "released": 1372172400
        }
      },
      {
        "title": "Cutie Panther",
        "artist": 3,
        "metadata": {
          "released": 1374591600
        }
      },
      {
        "title": "夏、終わらないで。",
        "title.ko": "여름, 끝나지 말아줘.",
        "artist": 3,
        "metadata": {
          "released": 1374591600
        }
      },
      {
        "title": "にこぷり♥女子道",
        "title.ko": "니코프리♥여자의 길",
        "artist": 13,
        "metadata": {
          "released": 1374764400
        }
      },
      {
        "title": "Pure girls project",
        "artist": 2,
        "metadata": {
          "released": 1377010800
        }
      },
      {
        "title": "UNBALANCED LOVE",
        "artist": 2,
        "metadata": {
          "released": 1377010800
        }
      },
      {
        "title": "硝子の花園",
        "title.ko": "유리의 화원",
        "artist": [6, 11],
        "metadata": {
          "released": 1377615600
        }
      },
      {
        "title": "LONELIEST BABY",
        "artist": 0,
        "metadata": {
          "released": 1380034800
        }
      },
      {
        "title": "ぷわぷわーお！",
        "title.ko": "푹신푹신-오!",
        "artist": 2,
        "metadata": {
          "released": 1380034800
        }
      },
      {
        "title": "Music S.T.A.R.T!!",
        "artist": 0,
        "metadata": {
          "released": 1385478000
        }
      },
      {
        "title": "LOVELESS WORLD",
        "artist": 0,
        "metadata": {
          "released": 1385478000
        }
      },
      {
        "title": "タカラモノズ",
        "title.ko": "보물들",
        "artist": 0,
        "metadata": {
          "released": 1390921200
        }
      },
      {
        "title": "Paradise Live",
        "artist": 0,
        "metadata": {
          "released": 1390921200
        }
      },
      {
        "title": "それは僕たちの奇跡",
        "title.ko": "그것은 우리들의 기적",
        "artist": 0,
        "metadata": {
          "released": 1398178800
        }
      },
      {
        "title": "だってだって噫無情",
        "title.ko": "그치만 그치만 아아 무정",
        "artist": 0,
        "metadata": {
          "released": 1398178800
        }
      },
      {
        "title": "どんなときもずっと",
        "title.ko": "어떤 때라도 계속",
        "artist": 0,
        "metadata": {
          "released": 1399474800
        }
      },
      {
        "title": "COLORFUL VOICE",
        "artist": 0,
        "metadata": {
          "released": 1399474800
        }
      },
      {
        "title": "ユメノトビラ",
        "title.ko": "꿈의 문",
        "artist": 0,
        "metadata": {
          "released": 1401202800
        }
      },
      {
        "title": "SENTIMENTAL StepS",
        "artist": 0,
        "metadata": {
          "released": 1401202800
        }
      },
      {
        "title": "Love wing bell",
        "artist": [6, 9, 10, 11, 12, 13],
        "metadata": {
          "released": 1402412400
        }
      },
      {
        "title": "Dancing stars on me!",
        "artist": 0,
        "metadata": {
          "released": 1402412400
        }
      },
      {
        "title": "シアワセ行きのSMILING!",
        "title.ko": "행복을 향한 SMILING!",
        "artist": 5,
        "metadata": {
          "released": 1403190000
        }
      },
      {
        "title": "KiRa-KiRa Sensation!",
        "artist": 0,
        "metadata": {
          "released": 1404831600
        }
      },
      {
        "title": "Happy maker!",
        "artist": 0,
        "metadata": {
          "released": 1404831600
        }
      },
      {
        "title": "ずるいよMagnetic today",
        "title.ko": "치사해 Magnetic today",
        "artist": [10, 13],
        "metadata": {
          "released": 1406214000
        }
      },
      {
        "title": "くるりんMIRACLE",
        "title.ko": "빙그르르 MIRACLE",
        "artist": 9,
        "metadata": {
          "released": 1409065200
        }
      },
      {
        "title": "Shocking Party",
        "artist": 1,
        "metadata": {
          "released": 1409065200
        }
      },
      {
        "title": "Storm in Lover",
        "artist": [6, 8],
        "metadata": {
          "released": 1411484400
        }
      },
      {
        "title": "Shangri-La Shower",
        "artist": 0,
        "metadata": {
          "released": 1412089200
        }
      },
      {
        "title": "もしもからきっと",
        "title.ko": "만약으로부터 분명",
        "artist": 11,
        "metadata": {
          "released": 1414508400
        }
      },
      {
        "title": "永遠フレンズ",
        "title.ko": "영원 프렌즈",
        "artist": 2,
        "metadata": {
          "released": 1415718000
        }
      },
      {
        "title": "小夜啼鳥恋詩",
        "title.ko": "나이팅게일 러브 송",
        "artist": 2,
        "metadata": {
          "released": 1415718000
        }
      },
      {
        "title": "好きですが好きですか？",
        "title.ko": "좋아하는데 좋아하나요?",
        "artist": [7, 12],
        "metadata": {
          "released": 1416495600
        }
      },
      {
        "title": "秋のあなたの空遠く",
        "title.ko": "가을의 당신의 하늘 저 멀리",
        "artist": 4,
        "metadata": {
          "released": 1416927600
        }
      },
      {
        "title": "ふたりハピネス",
        "title.ko": "두 사람 해피니스",
        "artist": 4,
        "metadata": {
          "released": 1416927600
        }
      },
      {
        "title": "冬がくれた予感",
        "title.ko": "겨울이 준 예감",
        "artist": 3,
        "metadata": {
          "released": 1419346800
        }
      },
      {
        "title": "Trouble Busters",
        "artist": 3,
        "metadata": {
          "released": 1419346800
        }
      },
      {
        "title": "CheerDay CheerGirl!",
        "artist": 2,
        "metadata": {
          "released": 1419433200
        }
      },
      {
        "title": "同じ星が見たい",
        "title.ko": "같은 별이 보고 싶어",
        "artist": 4,
        "metadata": {
          "released": 1419433200
        }
      },
      {
        "title": "Silent Tonight",
        "artist": 3,
        "metadata": {
          "released": 1419433200
        }
      },
      {
        "title": "そして最後のページには",
        "title.ko": "그리고 마지막 페이지에는",
        "artist": 0,
        "metadata": {
          "released": 1419433200
        }
      },
      {
        "title": "ミはμ’sicのミ",
        "title.ko": "미는 μ’sic의 미",
        "artist": 0,
        "metadata": {
          "released": 1429628400
        }
      },
      {
        "title": "Super LOVE＝Super LIVE!",
        "artist": 0,
        "metadata": {
          "released": 1429628400
        }
      },
      {
        "title": "最低で最高のParadiso",
        "title.ko": "최저이자 최고의 Paradiso",
        "artist": 3,
        "metadata": {
          "released": 1432306800
        }
      },
      {
        "title": "乙姫心で恋宮殿",
        "title.ko": "용녀 마음으로 사랑 궁전",
        "artist": 4,
        "metadata": {
          "released": 1432306800
        }
      },
      {
        "title": "MUSEUMでどうしたい",
        "title.ko": "MUSEUM에서 뭘하고 싶어?",
        "artist": 2,
        "metadata": {
          "released": 1432306800
        }
      },
      {
        "title": "Angelic Angel",
        "artist": 0,
        "metadata": {
          "released": 1435676400
        }
      },
      {
        "title": "Hello, 星を数えて",
        "title.ko": "Hello, 별을 세며",
        "artist": [9, 10, 12],
        "metadata": {
          "released": 1435676400
        }
      },
      {
        "title": "SUNNY DAY SONG",
        "artist": 0,
        "metadata": {
          "released": 1436281200
        }
      },
      {
        "title": "？←HEARTBEAT",
        "artist": [6, 11, 13],
        "metadata": {
          "released": 1436281200
        }
      },
      {
        "title": "僕たちはひとつの光",
        "title.ko": "우리는 하나의 빛",
        "artist": 0,
        "metadata": {
          "released": 1436886000
        }
      },
      {
        "title": "Future style",
        "artist": [5, 7, 8],
        "metadata": {
          "released": 1436886000
        }
      },
      {
        "title": "As Time Goes By",
        "artist": 0,
        "metadata": {
          "released": 1438700400
        }
      },
      {
        "title": "HEART to HEART!",
        "artist": 0,
        "metadata": {
          "released": 1445958000
        }
      },
      {
        "title": "嵐のなかの恋だから",
        "title.ko": "폭풍 속의 사랑이니까",
        "artist": 0,
        "metadata": {
          "released": 1445958000
        }
      },
      {
        "title": "WAO-WAO Powerful day!",
        "artist": 2,
        "metadata": {
          "released": 1448377200
        }
      },
      {
        "title": "NO EXIT ORION",
        "artist": 2,
        "metadata": {
          "released": 1448377200
        }
      },
      {
        "title": "これから",
        "title.ko": "지금부터",
        "artist": 0,
        "metadata": {
          "released": 1450105200
        }
      },
      {
        "title": "思い出以上になりたくて",
        "title.ko": "추억 이상이 되고 싶어서",
        "artist": 4,
        "metadata": {
          "released": 1450796400
        }
      },
      {
        "title": "春情ロマンティック",
        "title.ko": "춘정 로맨틱",
        "artist": 4,
        "metadata": {
          "released": 1450796400
        }
      },
      {
        "title": "錯覚CROSSROADS",
        "title.ko": "착각 CROSSROADS",
        "artist": 3,
        "metadata": {
          "released": 1453215600
        }
      },
      {
        "title": "PSYCHIC FIRE",
        "artist": 3,
        "metadata": {
          "released": 1453215600
        }
      },
      {
        "title": "MOMENT RING",
        "artist": 0,
        "metadata": {
          "released": 1456844400
        }
      },
      {
        "title": "さようならへさよなら！",
        "title.ko": "안녕이란 말에 안녕!",
        "artist": 0,
        "metadata": {
          "released": 1456844400
        }
      },
      {
        "title": "A Song for You! You? You!!",
        "artist": 0,
        "metadata": {
          "released": 1585062000
        }
      },
      {
        "title": "なってしまった！",
        "title.ko": "되어버렸다!",
        "artist": 0,
        "metadata": {
          "released": 1585062000
        }
      }
    ],
    [
      {
        "title": "君のこころは輝いてるかい？",
        "title.ko": "너의 마음은 빛나고 있니?",
        "artist": 0,
        "metadata": {
          "released": 1444176000
        }
      },
      {
        "title": "Step! ZERO to ONE",
        "artist": 0,
        "metadata": {
          "released": 1444176000
        }
      },
      {
        "title": "Aqours☆HEROES",
        "artist": 0,
        "metadata": {
          "released": 1444176000
        }
      },
      {
        "title": "恋になりたいAQUARIUM",
        "title.ko": "사랑이 되고 싶은 AQUARIUM",
        "artist": 0,
        "metadata": {
          "released": 1461715200
        }
      },
      {
        "title": "待ってて愛のうた",
        "title.ko": "기다려줘 사랑의 노래",
        "artist": 0,
        "metadata": {
          "released": 1461715200
        }
      },
      {
        "title": "届かない星だとしても",
        "title.ko": "닿을 수 없는 별이라 해도",
        "artist": 0,
        "metadata": {
          "released": 1461715200
        }
      },
      {
        "title": "元気全開DAY! DAY! DAY!",
        "title.ko": "원기전개 DAY! DAY! DAY!",
        "artist": 3,
        "metadata": {
          "released": 1462924800
        }
      },
      {
        "title": "夜空はなんでも知ってるの？",
        "title.ko": "밤하는을 뭐든지 알고 있는 거야?",
        "artist": 3,
        "metadata": {
          "released": 1462924800
        }
      },
      {
        "title": "トリコリコPLEASE!!",
        "title.ko": "토리코리코 PLEASE!!",
        "artist": 4,
        "metadata": {
          "released": 1464134400
        }
      },
      {
        "title": "ときめき分類学",
        "title.ko": "두근거림 분류학",
        "artist": 4,
        "metadata": {
          "released": 1464134400
        }
      },
      {
        "title": "Strawberry Trapper",
        "artist": 5,
        "metadata": {
          "released": 1465344000
        }
      },
      {
        "title": "Guilty Night, Guilty Kiss!",
        "artist": 5,
        "metadata": {
          "released": 1465344000
        }
      },
      {
        "title": "青空Jumping Heart",
        "title.ko": "푸른 하늘 Jumping Heart",
        "artist": 0,
        "metadata": {
          "released": 1468972800
        }
      },
      {
        "title": "ハミングフレンド",
        "title.ko": "허밍 프렌드",
        "artist": 0,
        "metadata": {
          "released": 1468972800
        }
      },
      {
        "title": "決めたよHand in Hand",
        "title.ko": "결정했어 Hand in Hand",
        "artist": [6, 7, 10],
        "metadata": {
          "released": 1470182400
        }
      },
      {
        "title": "ダイスキだったらダイジョウブ！",
        "title.ko": "정말로 좋아한다면 괜찮아!",
        "artist": [6, 7, 10],
        "metadata": {
          "released": 1470182400
        }
      },
      {
        "title": "ユメ語るよりユメ歌おう",
        "title.ko": "꿈을 말하기보다는 꿈을 노래하자",
        "artist": 0,
        "metadata": {
          "released": 1471996800
        }
      },
      {
        "title": "サンシャインぴっかぴか音頭",
        "title.ko": "선샤인 반짝반짝 선창",
        "artist": 0,
        "metadata": {
          "released": 1471996800
        }
      },
      {
        "title": "夢で夜空を照らしたい",
        "title.ko": "꿈으로 밤하늘을 비추고 싶어",
        "artist": [6, 7, 10, 11, 12, 14],
        "metadata": {
          "released": 1473811200
        }
      },
      {
        "title": "未熟DREAMER",
        "title.ko": "미숙 DREAMER",
        "artist": 0,
        "metadata": {
          "released": 1473811200
        }
      },
      {
        "title": "Pops heartで踊るんだもん！",
        "title.ko": "Pops heart로 춤추는걸!",
        "artist": 0,
        "metadata": {
          "released": 1474934400
        }
      },
      {
        "title": "空も心も晴れるから",
        "title.ko": "하늘도 마음도 맑을 테니까",
        "artist": [6, 7, 10],
        "metadata": {
          "released": 1477440000
        }
      },
      {
        "title": "想いよひとつになれ",
        "title.ko": "마음이여 하나가 되어라",
        "artist": [6, 8, 9, 10, 11, 12, 13, 14],
        "metadata": {
          "released": 1478649600
        }
      },
      {
        "title": "MIRAI TICKET",
        "artist": 0,
        "metadata": {
          "released": 1478649600
        }
      },
      {
        "title": "ジングルベルが止まらない",
        "title.ko": "징글벨이 멈추지 않아",
        "artist": 0,
        "metadata": {
          "released": 1479859200
        }
      },
      {
        "title": "聖なる日の祈り",
        "title.ko": "성스러운 날의 기도",
        "artist": 0,
        "metadata": {
          "released": 1479859200
        }
      },
      {
        "title": "Waku-Waku-Week!",
        "artist": [11, 12, 14],
        "metadata": {
          "released": 1480032000
        }
      },
      {
        "title": "Daydream Warrior",
        "artist": 0,
        "metadata": {
          "released": 1482364800
        }
      },
      {
        "title": "G線上のシンデレラ",
        "title.ko": "G선상의 신데렐라",
        "artist": [8, 9, 13],
        "metadata": {
          "released": 1485475200
        }
      },
      {
        "title": "スリリング・ワンウェイ",
        "title.ko": "스릴링・원 웨이",
        "artist": 0,
        "metadata": {
          "released": 1487894400
        }
      },
      {
        "title": "P.S.の向こう側",
        "title.ko": "P.S.의 건너편",
        "artist": 3,
        "metadata": {
          "released": 1490313600
        }
      },
      {
        "title": "LONELY TUNING",
        "artist": 4,
        "metadata": {
          "released": 1490313600
        }
      },
      {
        "title": "Guilty Eyes Fever",
        "artist": 5,
        "metadata": {
          "released": 1490313600
        }
      },
      {
        "title": "太陽を追いかけろ！",
        "title.ko": "태양을 쫓아가자!",
        "artist": 0,
        "metadata": {
          "released": 1490313600
        }
      },
      {
        "title": "HAPPY PARTY TRAIN",
        "artist": 0,
        "metadata": {
          "released": 1491350400
        }
      },
      {
        "title": "SKY JOURNEY",
        "artist": 0,
        "metadata": {
          "released": 1491350400
        }
      },
      {
        "title": "少女以上の恋がしたい",
        "title.ko": "소녀 이상의 사랑이 하고 싶어",
        "artist": 0,
        "metadata": {
          "released": 1491350400
        }
      },
      {
        "title": "近未来ハッピーエンド",
        "title.ko": "근미래 해피엔드",
        "artist": 3,
        "metadata": {
          "released": 1494374400
        }
      },
      {
        "title": "海岸通りで待ってるよ",
        "title.ko": "해안 도로에서 기다릴게",
        "artist": 3,
        "metadata": {
          "released": 1494374400
        }
      },
      {
        "title": "GALAXY HidE and SeeK",
        "artist": 4,
        "metadata": {
          "released": 1496188800
        }
      },
      {
        "title": "INNOCENT BIRD",
        "artist": 4,
        "metadata": {
          "released": 1496188800
        }
      },
      {
        "title": "コワレヤスキ",
        "title.ko": "부서지기 쉬운 사랑",
        "artist": 5,
        "metadata": {
          "released": 1498003200
        }
      },
      {
        "title": "Shadow gate to love",
        "artist": 5,
        "metadata": {
          "released": 1498003200
        }
      },
      {
        "title": "Landing action Yeah!!",
        "artist": 0,
        "metadata": {
          "released": 1498780800
        }
      },
      {
        "title": "夏の終わりの雨音が",
        "title.ko": "여름 끝의 빗소리가",
        "artist": [6, 8],
        "metadata": {
          "released": 1501632000
        }
      },
      {
        "title": "真夏は誰のモノ？",
        "title.ko": "한 여름은 누구의 것?",
        "artist": [9, 14],
        "metadata": {
          "released": 1501632000
        }
      },
      {
        "title": "地元愛♡満タン☆サマーライフ",
        "title.ko": "고향 사랑♡가득 담은☆서머 라이프",
        "artist": [10, 11],
        "metadata": {
          "released": 1501632000
        }
      },
      {
        "title": "夏への扉 Never end ver.",
        "title.ko": "여름으로의 문 Never end ver.",
        "artist": [7, 12, 13],
        "metadata": {
          "released": 1501632000
        }
      },
      {
        "title": "未来の僕らは知ってるよ",
        "title.ko": "미래의 우리는 알고 있어",
        "artist": 0,
        "metadata": {
          "released": 1508889600
        }
      },
      {
        "title": "君の瞳を巡る冒険",
        "title.ko": "너의 눈동자를 둘러싼 모험",
        "artist": 0,
        "metadata": {
          "released": 1508889600
        }
      },
      {
        "title": "勇気はどこに？君の胸に！",
        "title.ko": "용기는 어디에? 너의 가슴에!",
        "artist": 0,
        "metadata": {
          "released": 1510704000
        }
      },
      {
        "title": "MY舞☆TONIGHT",
        "title.ko": "MY무희☆TONIGHT",
        "artist": 0,
        "metadata": {
          "released": 1511913600
        }
      },
      {
        "title": "MIRACLE WAVE",
        "artist": 0,
        "metadata": {
          "released": 1511913600
        }
      },
      {
        "title": "Awaken the Power",
        "artist": 2,
        "metadata": {
          "released": 1513728000
        }
      },
      {
        "title": "CRASH MIND",
        "artist": 1,
        "metadata": {
          "released": 1513728000
        }
      },
      {
        "title": "One More Sunshine Story",
        "artist": 6,
        "metadata": {
          "released": 1513900800
        }
      },
      {
        "title": "WATER BLUE NEW WORLD",
        "artist": 0,
        "metadata": {
          "released": 1516233600
        }
      },
      {
        "title": "WONDERFUL STORIES",
        "artist": 0,
        "metadata": {
          "released": 1516233600
        }
      },
      {
        "title": "おやすみなさん！",
        "title.ko": "안녕히 주무세여러분!",
        "artist": 12,
        "metadata": {
          "released": 1516924800
        }
      },
      {
        "title": "in this unstable world",
        "artist": 11,
        "metadata": {
          "released": 1519344000
        }
      },
      {
        "title": "Pianoforte Monologue",
        "artist": 7,
        "metadata": {
          "released": 1519344000
        }
      },
      {
        "title": "Beginner's Sailing",
        "artist": 10,
        "metadata": {
          "released": 1521763200
        }
      },
      {
        "title": "RED GEM WINK",
        "artist": 14,
        "metadata": {
          "released": 1524528000
        }
      },
      {
        "title": "WHITE FIRST LOVE",
        "artist": 9,
        "metadata": {
          "released": 1524528000
        }
      },
      {
        "title": "New winding road",
        "artist": 13,
        "metadata": {
          "released": 1527206400
        }
      },
      {
        "title": "さかなかなんだか？",
        "title.ko": "물고기 카난일카?",
        "artist": 8,
        "metadata": {
          "released": 1527206400
        }
      },
      {
        "title": "サクラバイバイ",
        "title.ko": "벛꽃 바이바이",
        "artist": 3,
        "metadata": {
          "released": 1529625600
        }
      },
      {
        "title": "卒業ですね",
        "title.ko": "졸업이네요",
        "artist": 4,
        "metadata": {
          "released": 1529625600
        }
      },
      {
        "title": "Guilty!? Farewell Party",
        "artist": 5,
        "metadata": {
          "released": 1529625600
        }
      },
      {
        "title": "キセキヒカル",
        "title.ko": "기적, 빛나다",
        "artist": 0,
        "metadata": {
          "released": 1529625600
        }
      },
      {
        "title": "ホップ・ステップ・ワーイ！",
        "title.ko": "Hop・Step・와이!",
        "artist": 0,
        "metadata": {
          "released": 1530316800
        }
      },
      {
        "title": "ホップ・ステップ・ワーイ！ [CYaRon! Ver.]",
        "title.ko": "Hop・Step・와이! [CYaRon! Ver.]",
        "artist": 3,
        "metadata": {
          "released": 1530316800
        }
      },
      {
        "title": "ホップ・ステップ・ワーイ！  [AZALEA Ver.]",
        "title.ko": "Hop・Step・와이! [AZALEA Ver.]",
        "artist": 4,
        "metadata": {
          "released": 1530316800
        }
      },
      {
        "title": "ホップ・ステップ・ワーイ！ [Guilty Kiss Ver.]",
        "title.ko": "Hop・Step・와이! [Guilty Kiss Ver.]",
        "artist": 5,
        "metadata": {
          "released": 1530316800
        }
      },
      {
        "title": "Thank you, FRIENDS!!",
        "artist": 0,
        "metadata": {
          "released": 1533081600
        }
      },
      {
        "title": "No.10",
        "artist": 0,
        "metadata": {
          "released": 1533081600
        }
      },
      {
        "title": "ハジマリロード",
        "title.ko": "시작의 길",
        "artist": [11, 12, 14],
        "metadata": {
          "released": 1543017600
        }
      },
      {
        "title": "Marine Border Parasol",
        "artist": [6, 7, 10],
        "metadata": {
          "released": 1543017600
        }
      },
      {
        "title": "予測不可能Driving!",
        "title.ko": "예측 불가능 Driving!",
        "artist": [8, 9, 13],
        "metadata": {
          "released": 1543017600
        }
      },
      {
        "title": "僕らの走ってきた道は…",
        "title.ko": "우리가 달려온 길은…",
        "artist": 0,
        "metadata": {
          "released": 1548201600
        }
      },
      {
        "title": "Next SPARKLING!!",
        "artist": 0,
        "metadata": {
          "released": 1548201600
        }
      },
      {
        "title": "逃走迷走メビウスループ",
        "title.ko": "도망 황망 뫼비우스의 띠",
        "artist": [8, 9, 13],
        "metadata": {
          "released": 1548806400
        }
      },
      {
        "title": "Hop? Stop? Nonstop!",
        "artist": 0,
        "metadata": {
          "released": 1548806400
        }
      },
      {
        "title": "Believe Again",
        "artist": 1,
        "metadata": {
          "released": 1549411200
        }
      },
      {
        "title": "Brightest Melody",
        "artist": 0,
        "metadata": {
          "released": 1549411200
        }
      },
      {
        "title": "Over The Next Rainbow",
        "artist": 2,
        "metadata": {
          "released": 1549411200
        }
      },
      {
        "title": "Jump up HIGH!!",
        "artist": 0,
        "metadata": {
          "released": 1561852800
        }
      },
      {
        "title": "\"I-n-g, I Try!!\"",
        "artist": 0,
        "metadata": {
          "released": 1564099200
        }
      },
      {
        "title": "未体験HORIZON",
        "title.ko": "미체험 HORIZON",
        "artist": 0,
        "metadata": {
          "released": 1569369600
        }
      },
      {
        "title": "Deep Resonance",
        "artist": 0,
        "metadata": {
          "released": 1569369600
        }
      },
      {
        "title": "Dance with Minotaurus",
        "artist": 0,
        "metadata": {
          "released": 1569369600
        }
      },
      {
        "title": "KOKORO Magic “A to Z”",
        "artist": 0,
        "metadata": {
          "released": 1572393600
        }
      },
      {
        "title": "New Romantic Sailors",
        "artist": 5,
        "metadata": {
          "released": 1574812800
        }
      },
      {
        "title": "Love Pulsar",
        "artist": 5,
        "metadata": {
          "released": 1574812800
        }
      },
      {
        "title": "Braveheart Coaster",
        "artist": 3,
        "metadata": {
          "released": 1575417600
        }
      },
      {
        "title": "CHANGELESS",
        "artist": 3,
        "metadata": {
          "released": 1575417600
        }
      },
      {
        "title": "Amazing Travel DNA",
        "artist": 4,
        "metadata": {
          "released": 1576022400
        }
      },
      {
        "title": "空中恋愛論",
        "title.ko": "공중연애론",
        "artist": 4,
        "metadata": {
          "released": 1576022400
        }
      },
      {
        "title": "シャゼリア☆キッス☆ダダンダーン",
        "title.ko": "샤젤리아☆키스☆다당당",
        "artist": 4,
        "metadata": {
          "released": 1588896000
        }
      },
      {
        "title": "Fantastic Departure!",
        "artist": 0,
        "metadata": {
          "released": 1595376000
        }
      },
      {
        "title": "Aqours Pirates Desire",
        "artist": 0,
        "metadata": {
          "released": 1595376000
        }
      },
      {
        "title": "Never giving up!",
        "artist": 6,
        "metadata": {
          "released": 1596240000
        }
      },
      {
        "title": "Dazzling White Town",
        "artist": 1,
        "metadata": {
          "released": 1597795200
        }
      },
      {
        "title": "Lonely Snow Planet",
        "artist": 1,
        "metadata": {
          "released": 1597795200
        }
      },
      {
        "title": "After The Rain",
        "artist": 1,
        "metadata": {
          "released": 1597795200
        }
      },
      {
        "title": "JIMO-AI Dash!",
        "artist": 0,
        "metadata": {
          "released": 1598400000
        }
      },
      {
        "title": "PURE PHRASE",
        "artist": 7,
        "metadata": {
          "released": 1600473600
        }
      },
      {
        "title": "コットンキャンディえいえいおー!",
        "title.ko": "코튼 캔디 에이 에이 오!",
        "artist": 14,
        "metadata": {
          "released": 1600646400
        }
      },
      {
        "title": "Future flight",
        "artist": 0,
        "metadata": {
          "released": 1600646400
        }
      },
      {
        "title": "Misty Frosty Love",
        "artist": [7, 10],
        "metadata": {
          "released": 1607472000
        }
      },
      {
        "title": "涙が雪になる前に",
        "title.ko": "눈물이 눈이 되기 전에",
        "artist": [8, 13],
        "metadata": {
          "released": 1607472000
        }
      },
      {
        "title": "キモチもユメも一緒だね！",
        "title.ko": "마음도 꿈도 함께네!",
        "artist": [12, 14],
        "metadata": {
          "released": 1607472000
        }
      },
      {
        "title": "Party! Party! PaPaPaParty!",
        "artist": [6, 9, 11],
        "metadata": {
          "released": 1607472000
        }
      },
      {
        "title": "Perfect SEKAI",
        "artist": 9,
        "metadata": {
          "released": 1609459200
        }
      },
      {
        "title": "もっとね!",
        "title.ko": "조금 더!",
        "artist": 8,
        "metadata": {
          "released": 1612915200
        }
      },
      {
        "title": "あこがれランララン",
        "title.ko": "동경 란라란",
        "artist": 12,
        "metadata": {
          "released": 1614816000
        }
      },
      {
        "title": "smile smile ship Start!",
        "artist": 0,
        "metadata": {
          "released": 1617148800
        }
      },
      {
        "title": "心の羽よ君へ飛んでけ！",
        "title.ko": "마음의 날개여 너에게 날아가라!",
        "artist": 0,
        "metadata": {
          "released": 1617148800
        }
      },
      {
        "title": "突然GIRL",
        "title.ko": "돌연 GIRL",
        "artist": 10,
        "metadata": {
          "released": 1618617600
        }
      },
      {
        "title": "오하라 마리 신곡",
        "artist": 13,
        "metadata": {
          "released": 1623542400
        }
      },
      {
        "title": "츠시마 요시코 신곡",
        "artist": 11,
        "metadata": {
          "released": 1626134400
        }
      }
    ],
    [],
    []
  ]
}
